{"564883494103416833":{"kategoria":"Anime","zaproszenie":"asd","opis":"[tutaj opis]","test-opis":"bksdaj \n sjaldn","czymozna":1,"zalozyciel":"419543440343433227"},"570892549686820877":{"kategoria":"Filmy","zaproszenie":"https://discord.gg/c9ZpPY6","czymozna":1,"zalozyciel":"454947172685971486","opis":"Lubie Placki\n XDDDD 😂"},"570972862316412948":{"kategoria":"Community","zaproszenie":"https://discord.gg/aa4fphn","czymozna":1,"zalozyciel":"419543440343433227","opis":"Lubje Placuszki XDDD\n __wiem że ty też__\n więc dołącz na nasz serwer"}}